{
    "2nd Quarter 2012 Consolidated Net Income (Loss)": {
        "(In Thousands)": 308525
    },
    "Net revenue (operating revenue less fuelexpense, purchased power, and otherregulatory charges/credits)": {
        "(In Thousands)": 219043
    },
    "Other operation and maintenance expenses": {
        "(In Thousands)": 65119
    },
    "Taxes other than income taxes": {
        "(In Thousands)": 7095
    },
    "Depreciation and amortization": {
        "(In Thousands)": 20634
    },
    "Other income": {
        "(In Thousands)": 4133
    },
    "Interest expense": {
        "(In Thousands)": 9989
    },
    "Other expenses": {
        "(In Thousands)": 4922
    },
    "Income taxes": {
        "(In Thousands)": 223387
    },
    "2nd Quarter 2013 Consolidated Net Income (Loss)": {
        "(In Thousands)": 200555
    }
}