{
    "": {
        "Three Months Ended March 31,": "-in millions except per share amounts"
    },
    "Revenues:": {},
    "Expenses:": {},
    "Other Income -Expense:": {},
    "Basic earnings  per common share - continuing operations": {},
    "Basic earnings per common share - discontinued operations": {
        "Three Months Ended March 31,": ""
    },
    "Basic Earnings Per Common Share": {},
    "Diluted earnings per common share - continuing operations": {},
    "Diluted earnings per common share - discontinued operations": {
        "Three Months Ended March 31,": ""
    },
    "Diluted Earnings Per Common Share": {}
}